n_numero_primo/n_numero_primo.py
n_numero_primo-1.0.dist-info/LICENSE
n_numero_primo-1.0.dist-info/METADATA
n_numero_primo-1.0.dist-info/WHEEL
n_numero_primo-1.0.dist-info/top_level.txt
n_numero_primo-1.0.dist-info/RECORD
