Metadata-Version: 2.1
Name: n-numero-primo
Version: 1.0
Summary: Encontrar numeros primos desde 1 hasta n.
Home-page: UNKNOWN
Author: Brener sanchez 
Author-email: bsanchezt@unc.edu.pe
License: GNU GPLv3
Keywords: primo numeros primos desde 1 hasta n
Platform: UNKNOWN
Classifier: Development Status :: 4 - Beta
Classifier: Intended Audience :: Developers
Classifier: Topic :: Utilities
Classifier: License :: OSI Approved :: GNU General Public License v3 (GPLv3)
Classifier: Programming Language :: Python :: 3
Classifier: Operating System :: OS Independent
License-File: LICENSE
